creolenltk/__init__.py
creolenltk/contraction_expansion.py
creolenltk/num2word.py
creolenltk/number_dict.py
creolenltk/spelling_checker.py
creolenltk/stopword.py
creolenltk/text_cleaner.py
creolenltk/tokenizer.py
creolenltk/data/creole_stopwords.txt
creolenltk/data/creole_words.txt
creolenltk/pos/__init__.py
creolenltk/pos/merge_ud_corpora.py
creolenltk/pos/pos_tagger.py
creolenltk/pos/prepare_data.py
creolenltk/pos/train.py
creolenltk/pos/model-best/dev.spacy
creolenltk/pos/model-best/test.spacy
creolenltk/pos/model-best/train.spacy
creolenltk/pos/model-best/model-best/config.cfg
creolenltk/pos/model-best/model-best/meta.json
creolenltk/pos/model-best/model-best/tokenizer
creolenltk/pos/model-best/model-best/tagger/cfg
creolenltk/pos/model-best/model-best/tagger/model
creolenltk/pos/model-best/model-best/tok2vec/cfg
creolenltk/pos/model-best/model-best/tok2vec/model
creolenltk/pos/model-best/model-best/vocab/key2row
creolenltk/pos/model-best/model-best/vocab/lookups.bin
creolenltk/pos/model-best/model-best/vocab/strings.json
creolenltk/pos/model-best/model-best/vocab/vectors
creolenltk/pos/model-best/model-best/vocab/vectors.cfg
creolenltk/pos/model-best/model-last/config.cfg
creolenltk/pos/model-best/model-last/meta.json
creolenltk/pos/model-best/model-last/tokenizer
creolenltk/pos/model-best/model-last/tagger/cfg
creolenltk/pos/model-best/model-last/tagger/model
creolenltk/pos/model-best/model-last/tok2vec/cfg
creolenltk/pos/model-best/model-last/tok2vec/model
creolenltk/pos/model-best/model-last/vocab/key2row
creolenltk/pos/model-best/model-last/vocab/lookups.bin
creolenltk/pos/model-best/model-last/vocab/strings.json
creolenltk/pos/model-best/model-last/vocab/vectors
creolenltk/pos/model-best/model-last/vocab/vectors.cfg
creolenltk-1.0.10.dist-info/licenses/LICENSE
tests/__init__.py
tests/test_cleaner.py
tests/test_contraction_expansion.py
tests/test_num2words.py
tests/test_pos_tagger.py
tests/test_spelling_checker.py
tests/test_stopwords.py
tests/test_tokenizer.py
creolenltk-1.0.10.dist-info/METADATA
creolenltk-1.0.10.dist-info/WHEEL
creolenltk-1.0.10.dist-info/top_level.txt
creolenltk-1.0.10.dist-info/RECORD
