Metadata-Version: 2.4
Name: creolenltk
Version: 1.0.10
Summary: A Python library for Creole text preprocessing
Home-page: https://github.com/bjclayton/CreoleNLTK.git
Author: John Clayton
Author-email: John Clayton <jclaytonblanc@gmail.com>
License: Copyright 2024 John Clayton
Keywords: python,nlp,creole,natural language processing,text preprocessing
Classifier: Programming Language :: Python :: 3
Classifier: License :: OSI Approved :: MIT License
Classifier: Operating System :: OS Independent
Requires-Python: >=3.6
License-File: LICENSE
Requires-Dist: beautifulsoup4>=4.9.3
Requires-Dist: nltk>=3.6.2
Requires-Dist: spacy>=3.7.2
Requires-Dist: conllu
Dynamic: author
Dynamic: home-page
Dynamic: license-file
Dynamic: requires-python
